panelstatus/__init__.py
panelstatus/gnome_extension/extension.js
panelstatus/gnome_extension/metadata.json
panelstatus-1.1.0.dist-info/licenses/LICENSE
panelstatus-1.1.0.dist-info/METADATA
panelstatus-1.1.0.dist-info/WHEEL
panelstatus-1.1.0.dist-info/entry_points.txt
panelstatus-1.1.0.dist-info/top_level.txt
panelstatus-1.1.0.dist-info/RECORD
