Metadata-Version: 2.4
Name: panelstatus
Version: 1.1.0
Summary: Dead simple GNOME panel status updates - inspired by ggplot2
Author-email: Maxime Rivest <mrive052@gmail.com>
License: MIT
Project-URL: Homepage, https://github.com/maximerivest/panelstatus
Project-URL: Repository, https://github.com/maximerivest/panelstatus
Project-URL: Issues, https://github.com/maximerivest/panelstatus/issues
Keywords: gnome,status,panel,notification,gui
Classifier: Development Status :: 4 - Beta
Classifier: Intended Audience :: Developers
Classifier: License :: OSI Approved :: MIT License
Classifier: Programming Language :: Python :: 3
Classifier: Programming Language :: Python :: 3.7
Classifier: Programming Language :: Python :: 3.8
Classifier: Programming Language :: Python :: 3.9
Classifier: Programming Language :: Python :: 3.10
Classifier: Programming Language :: Python :: 3.11
Classifier: Operating System :: POSIX :: Linux
Classifier: Topic :: Software Development :: User Interfaces
Requires-Python: >=3.7
License-File: LICENSE
Dynamic: license-file
